zabel/fabric/__init__.py
zabel/fabric/standalone/__init__.py
zabel/fabric/standalone/coreapis.yaml
zabel/fabric/standalone/environ.py
zabel/fabric/standalone/etcd3.py
zabel/fabric/standalone/openapi.py
zabel/fabric/standalone/resolver.py
zabel_fabric-0.16.1.dist-info/LICENSE.txt
zabel_fabric-0.16.1.dist-info/METADATA
zabel_fabric-0.16.1.dist-info/WHEEL
zabel_fabric-0.16.1.dist-info/top_level.txt
zabel_fabric-0.16.1.dist-info/RECORD
