Metadata-Version: 2.1
Name: zabel-fabric
Version: 0.16.1
Summary: The Zabel Fabric
Home-page: https://github.com/engie-group/zabel
Author: Martin Lafaix
Author-email: martin.lafaix@external.engie.com
License: Eclipse Public License 2.0
Platform: UNKNOWN
Classifier: Development Status :: 4 - Beta
Classifier: Programming Language :: Python :: 3
Classifier: License :: OSI Approved :: Eclipse Public License 2.0 (EPL-2.0)
Classifier: Operating System :: OS Independent
Classifier: Topic :: Software Development :: Libraries
Requires-Python: >= 3.6.5
Requires-Dist: requests (>=2.23)
Requires-Dist: bottle (>=0.12)
Requires-Dist: zabel-commons (>=1.4)
Requires-Dist: PyJWT (>=1.7.1)
Requires-Dist: PyYAML (>=5.3)
